LICENSE
README.md
setup.py
py_timed_cache.egg-info/PKG-INFO
py_timed_cache.egg-info/SOURCES.txt
py_timed_cache.egg-info/dependency_links.txt
py_timed_cache.egg-info/top_level.txt
tests/__init__.py
tests/context.py
tests/test_timedcache.py
timedcache/__init__.py
timedcache/timedcache.py