Metadata-Version: 2.1
Name: py-timed-cache
Version: 1.0.2
Summary: Pure Python timed-cache
Home-page: https://github.com/NicoAdrian/timed-cache
Author: Nicolas Adrian
Author-email: nicolasadrian3@gmail.com
License: MIT
Keywords: cache,timed-cache,timedcache
License-File: LICENSE
